fcw_core_utils/__init__.py
fcw_core_utils/collision.py
fcw_core_utils/geometry.py
fcw_core_utils/rate_timer.py
fcw_core_utils-0.12.1.dist-info/METADATA
fcw_core_utils-0.12.1.dist-info/WHEEL
fcw_core_utils-0.12.1.dist-info/RECORD
